framulent/VERSION
framulent/__init__.py
framulent/engine.py
framulent/mypy_plugin.py
framulent/py.typed
framulent-0.0.1.dist-info/LICENSE
framulent-0.0.1.dist-info/METADATA
framulent-0.0.1.dist-info/WHEEL
framulent-0.0.1.dist-info/top_level.txt
framulent-0.0.1.dist-info/RECORD
