Metadata-Version: 2.1
Name: framulent
Version: 0.0.1
Summary: Cromulent Dataframe Computing
Home-page: https://github.com/miiohio/framulent
Author: William Harvey
Author-email: drwjharvey@gmail.com
License: UNKNOWN
Platform: UNKNOWN
License-File: LICENSE
Requires-Dist: duckdb (>=0.3.4)
Requires-Dist: mypy (>=0.942)
Requires-Dist: typing-extensions (>=4.2.0)
